MacroLib/MacroLib.py
MacroLib/__init__.py
MacroLib-1.0.0.dist-info/LICENSE
MacroLib-1.0.0.dist-info/METADATA
MacroLib-1.0.0.dist-info/WHEEL
MacroLib-1.0.0.dist-info/top_level.txt
MacroLib-1.0.0.dist-info/RECORD
