Metadata-Version: 2.1
Name: MacroLib
Version: 1.0.0
Summary: Streaming video data via networks
Home-page: UNKNOWN
Author: Mafuyu / NotaDev
Author-email: <companioncubegd@gmail.com>
License: UNKNOWN
Keywords: python,macro,automation
Platform: UNKNOWN
Classifier: Development Status :: 1 - Planning
Classifier: Intended Audience :: Developers
Classifier: Programming Language :: Python :: 3
Classifier: Operating System :: Unix
Classifier: Operating System :: MacOS :: MacOS X
Classifier: Operating System :: Microsoft :: Windows
Requires-Dist: caer
Requires-Dist: opencv-python
Requires-Dist: pyautogui
